osta/__init__.py
osta/__utils.py
osta/__utils_enrich.py
osta/__utils_imports.py
osta/__utils_wrangle.py
osta/enrich.py
osta/imports.py
osta/resources.py
osta/wrangle.py
osta/resources/data_account.csv
osta/resources/data_financial.csv
osta/resources/data_land.csv
osta/resources/data_municipality.csv
osta/resources/data_service.csv
osta/resources/fields_export.csv
osta/resources/fields_mandatory.csv
osta/resources/fields_optional.csv
osta/resources/fields_pairs.csv
osta-0.6.16.dist-info/LICENSE
osta-0.6.16.dist-info/METADATA
osta-0.6.16.dist-info/WHEEL
osta-0.6.16.dist-info/top_level.txt
osta-0.6.16.dist-info/RECORD
