Metadata-Version: 2.1
Name: osta
Version: 0.6.16
Summary: OSTolaskujen Analysointi -- package for analysing invoices of Finnish public organizations
Home-page: https://github.com/TuomasBorman/osta
Author: Tuomas Borman
Author-email: tvborm@utu.fi
License: Artistic License 2.0
Platform: unix
Platform: linux
Platform: osx
Platform: cygwin
Platform: win32
Classifier: Programming Language :: Python :: 3.8
Classifier: Programming Language :: Python :: 3.9
Requires-Python: >=3.8
License-File: LICENSE
